{
  "hash": "edf37f33",
  "browserHash": "d792c269",
  "optimized": {
    "vue": {
      "src": "../../../node_modules/vue/dist/vue.runtime.esm-bundler.js",
      "file": "vue.js",
      "fileHash": "e4f72563",
      "needsInterop": false
    },
    "echarts": {
      "src": "../../../node_modules/echarts/index.js",
      "file": "echarts.js",
      "fileHash": "c8214bad",
      "needsInterop": false
    },
    "@stackblitz/sdk": {
      "src": "../../../node_modules/@stackblitz/sdk/bundles/sdk.m.js",
      "file": "@stackblitz_sdk.js",
      "fileHash": "f9d5884d",
      "needsInterop": false
    }
  },
  "chunks": {
    "chunk-JC4IRQUL": {
      "file": "chunk-JC4IRQUL.js"
    }
  }
}